unitycatalog/__init__.py
unitycatalog/_base_client.py
unitycatalog/_client.py
unitycatalog/_compat.py
unitycatalog/_constants.py
unitycatalog/_exceptions.py
unitycatalog/_files.py
unitycatalog/_models.py
unitycatalog/_qs.py
unitycatalog/_resource.py
unitycatalog/_response.py
unitycatalog/_streaming.py
unitycatalog/_types.py
unitycatalog/_version.py
unitycatalog/py.typed
unitycatalog/_utils/__init__.py
unitycatalog/_utils/_logs.py
unitycatalog/_utils/_proxy.py
unitycatalog/_utils/_streams.py
unitycatalog/_utils/_sync.py
unitycatalog/_utils/_transform.py
unitycatalog/_utils/_typing.py
unitycatalog/_utils/_utils.py
unitycatalog/lib/.keep
unitycatalog/resources/__init__.py
unitycatalog/resources/catalogs.py
unitycatalog/resources/functions.py
unitycatalog/resources/schemas.py
unitycatalog/resources/tables.py
unitycatalog/resources/temporary_table_credentials.py
unitycatalog/resources/temporary_volume_credentials.py
unitycatalog/resources/volumes.py
unitycatalog/types/__init__.py
unitycatalog/types/catalog_create_params.py
unitycatalog/types/catalog_delete_params.py
unitycatalog/types/catalog_info.py
unitycatalog/types/catalog_list_params.py
unitycatalog/types/catalog_list_response.py
unitycatalog/types/catalog_update_params.py
unitycatalog/types/function_create_params.py
unitycatalog/types/function_info.py
unitycatalog/types/function_list_params.py
unitycatalog/types/function_list_response.py
unitycatalog/types/generate_temporary_table_credential_response.py
unitycatalog/types/generate_temporary_volume_credential_response.py
unitycatalog/types/schema_create_params.py
unitycatalog/types/schema_info.py
unitycatalog/types/schema_list_params.py
unitycatalog/types/schema_list_response.py
unitycatalog/types/schema_update_params.py
unitycatalog/types/table_create_params.py
unitycatalog/types/table_info.py
unitycatalog/types/table_list_params.py
unitycatalog/types/table_list_response.py
unitycatalog/types/temporary_table_credential_create_params.py
unitycatalog-0.1.1.dist-info/METADATA
unitycatalog-0.1.1.dist-info/WHEEL
unitycatalog-0.1.1.dist-info/licenses/LICENSE
unitycatalog-0.1.1.dist-info/RECORD
